ptadapter/__init__.py
ptadapter/__main__.py
ptadapter/adapters.py
ptadapter/console_script.py
ptadapter/contexts.py
ptadapter/enums.py
ptadapter/exceptions.py
ptadapter/log.py
ptadapter/relays.py
ptadapter/socks.py
ptadapter/str_utils.py
ptadapter-3.0.1.dist-info/LICENSE
ptadapter-3.0.1.dist-info/METADATA
ptadapter-3.0.1.dist-info/WHEEL
ptadapter-3.0.1.dist-info/entry_points.txt
ptadapter-3.0.1.dist-info/top_level.txt
ptadapter-3.0.1.dist-info/RECORD
