Metadata-Version: 2.1
Name: ptadapter
Version: 3.0.1
Summary: Pluggable Transports Python interface & standalone tunnels
Home-page: https://github.com/twisteroidambassador/ptadapter
Author: twisteroid ambassador
Author-email: twisteroid.ambassador@gmail.com
License: GPLv3
Project-URL: Tracker, https://github.com/twisteroidambassador/ptadapter/issues
Project-URL: Documentation, https://twisteroidambassador.github.io/ptadapter-docs/
Keywords: pluggable-transport obfuscation tcp
Classifier: Development Status :: 4 - Beta
Classifier: Intended Audience :: Developers
Classifier: Intended Audience :: End Users/Desktop
Classifier: Framework :: AsyncIO
Classifier: License :: OSI Approved :: GNU General Public License v3 (GPLv3)
Classifier: Programming Language :: Python :: 3 :: Only
Classifier: Programming Language :: Python :: 3.7
Classifier: Programming Language :: Python :: 3.8
Classifier: Programming Language :: Python :: 3.9
Classifier: Programming Language :: Python :: 3.10
Classifier: Programming Language :: Python :: 3.11
Classifier: Programming Language :: Python :: 3.12
Classifier: Topic :: Internet :: Proxy Servers
Requires-Python: >=3.7
License-File: LICENSE
Provides-Extra: build-docs
Requires-Dist: sphinx-autodoc-typehints ; extra == 'build-docs'
Requires-Dist: sphinxcontrib-trio ; extra == 'build-docs'
